lscmf/__about__.py
lscmf/__init__.py
lscmf/functional.py
lscmf/helpers.py
lscmf/lscmf.py
lscmf/matching.py
lscmf/preprocess.py
lscmf/scaling.py
lscmf/shrinkers.py
lscmf/simulate.py
lscmf/graphs/__init__.py
lscmf/graphs/base.py
lscmf/graphs/hyper.py
lscmf/graphs/match.py
lscmf/graphs/multi.py
lscmf/graphs/undirected.py
lscmf/graphs/view.py
lscmf-0.2.1.post1.dist-info/METADATA
lscmf-0.2.1.post1.dist-info/WHEEL
lscmf-0.2.1.post1.dist-info/licenses/LICENSE
lscmf-0.2.1.post1.dist-info/RECORD
