Metadata-Version: 2.4
Name: lscmf
Version: 0.2.1.post1
Summary: Performs large-scale CMF on flexible data layouts.
Project-URL: Documentation, https://cyianor.github.io/lscmf
Project-URL: Source, https://github.com/cyianor/lscmf
Project-URL: Bug Tracker, https://github.com/cyianor/lscmf/issues
Author-email: Felix Held <felix.held@gmail.com>
License-Expression: MIT
License-File: LICENSE
Classifier: License :: OSI Approved :: MIT License
Classifier: Operating System :: OS Independent
Classifier: Programming Language :: Python :: 3
Requires-Python: >=3.10
Requires-Dist: numpy>=1.23
Requires-Dist: scikit-learn>=1.1.0
Requires-Dist: scipy>=1.9
Requires-Dist: typing-extensions>=4.9.0; python_version < '3.11'
